{
  "schema_version": "0.1.0",
  "meta": {
    "source": "dxf",
    "source_ref": "apartment_third_floor_insert_blocks.dxf",
    "units": "mm"
  },
  "walls": [
    {
      "id": "12E3:1",
      "points": [
        [
          -5119.0,
          1875.0
        ],
        [
          -4235.0,
          1875.0
        ]
      ],
      "width": 250.0
    },
    {
      "id": "12E3:2",
      "points": [
        [
          -5244.0,
          -1750.0
        ],
        [
          -5244.0,
          1750.0
        ]
      ],
      "width": 250.0
    },
    {
      "id": "12E3:3",
      "points": [
        [
          -5119.0,
          -1809.5
        ],
        [
          -3119.0,
          -1809.5
        ]
      ],
      "width": 119.0
    },
    {
      "id": "12E3:4",
      "points": [
        [
          -3059.0,
          -3490.0
        ],
        [
          -3059.0,
          -1869.0
        ]
      ],
      "width": 120.0
    },
    {
      "id": "12E3:8",
      "points": [
        [
          -5244.0,
          -4869.0
        ],
        [
          -5244.0,
          -1869.0
        ]
      ],
      "width": 250.0
    },
    {
      "id": "12E3:9",
      "points": [
        [
          -5119.0,
          -4991.75
        ],
        [
          -3119.0,
          -4991.75
        ]
      ],
      "width": 250.0
    },
    {
      "id": "12E3:10",
      "points": [
        [
          -3059.0,
          -4860.0
        ],
        [
          -3059.0,
          -4390.0
        ]
      ],
      "width": 120.0
    },
    {
      "id": "12E3:13",
      "points": [
        [
          -2999.0,
          -4991.75
        ],
        [
          -2333.0,
          -4991.75
        ]
      ],
      "width": 259.0
    },
    {
      "id": "12E4:1",
      "points": [
        [
          -750.0,
          -4991.75
        ],
        [
          2000.0,
          -4991.75
        ]
      ],
      "width": 250.0
    },
    {
      "id": "12E4:1:m2",
      "points": [
        [
          -1433.0,
          -4991.75
        ],
        [
          -869.0,
          -4991.75
        ]
      ],
      "width": 259.0
    },
    {
      "id": "12E4:4",
      "points": [
        [
          -809.5,
          -4860.0
        ],
        [
          -809.5,
          -1870.0
        ]
      ],
      "width": 119.0
    },
    {
      "id": "12E4:5",
      "points": [
        [
          -1099.0,
          -1809.5
        ],
        [
          -869.0,
          -1809.5
        ]
      ],
      "width": 120.0
    },
    {
      "id": "12E4:7",
      "points": [
        [
          -750.0,
          -1809.5
        ],
        [
          -473.0,
          -1809.5
        ]
      ],
      "width": 119.0
    },
    {
      "id": "12E4:12",
      "points": [
        [
          2125.0,
          -4869.0
        ],
        [
          2125.0,
          -1869.0
        ]
      ],
      "width": 250.0
    },
    {
      "id": "12E4:13",
      "points": [
        [
          426.0,
          -1809.5
        ],
        [
          2000.0,
          -1809.5
        ]
      ],
      "width": 119.0
    },
    {
      "id": "12E4:16",
      "points": [
        [
          2125.0,
          -1750.0
        ],
        [
          2125.0,
          1750.0
        ]
      ],
      "width": 250.0
    },
    {
      "id": "12E4:17",
      "points": [
        [
          766.0,
          1875.0
        ],
        [
          2000.0,
          1875.0
        ]
      ],
      "width": 250.0
    },
    {
      "id": "12E5:1",
      "points": [
        [
          -2000.0,
          1875.0
        ],
        [
          -766.0,
          1875.0
        ]
      ],
      "width": 250.0
    },
    {
      "id": "12E5:2",
      "points": [
        [
          -2059.5,
          -1750.0
        ],
        [
          -2059.5,
          1750.0
        ]
      ],
      "width": 119.0
    },
    {
      "id": "12E5:3",
      "points": [
        [
          -2000.0,
          -1750.0
        ],
        [
          -1999.0,
          -1750.0
        ]
      ],
      "width": 119.0
    },
    {
      "id": "12E5:7",
      "points": [
        [
          -3061.0,
          1875.0
        ],
        [
          -2119.0,
          1875.0
        ]
      ],
      "width": 250.0
    }
  ],
  "doors": [
    {
      "id": "12E8",
      "points": [
        [
          -2000.0,
          -1810.0
        ],
        [
          -1099.999962,
          -1810.0
        ]
      ],
      "width": 900.0,
      "rooms": [
        "room_1",
        "room_3"
      ],
      "opens_towards_room": "room_1",
      "swing": "single_swing",
      "hinge_side": "end"
    },
    {
      "id": "12ED",
      "points": [
        [
          -2999.989848,
          -1810.0
        ],
        [
          -2099.99,
          -1810.0
        ]
      ],
      "width": 900.0,
      "rooms": [
        "room_2",
        "room_3"
      ],
      "opens_towards_room": "room_2",
      "swing": "single_swing",
      "hinge_side": "start"
    },
    {
      "id": "12F4",
      "points": [
        [
          -473.175018,
          -1809.99989
        ],
        [
          426.82,
          -1810.0
        ]
      ],
      "width": 899.995,
      "rooms": [
        "room_1",
        "room_5"
      ],
      "opens_towards_room": "room_5",
      "swing": "single_swing",
      "hinge_side": "start"
    },
    {
      "id": "12F7",
      "points": [
        [
          -3060.0,
          -4390.69
        ],
        [
          -3059.99989,
          -3490.689932
        ]
      ],
      "width": 900.0,
      "rooms": [
        "room_3",
        "room_4"
      ],
      "opens_towards_room": "room_4",
      "swing": "single_swing",
      "hinge_side": "end"
    },
    {
      "id": "12FC",
      "points": [
        [
          -2333.0,
          -4991.75
        ],
        [
          -1433.0,
          -4991.75
        ]
      ],
      "width": 900.0,
      "rooms": [
        "room_3"
      ]
    }
  ],
  "windows": [
    {
      "id": "12E7",
      "points": [
        [
          -766.0,
          1875.0
        ],
        [
          766.0,
          1875.0
        ]
      ],
      "width": 1532.0,
      "room": "room_1"
    },
    {
      "id": "12EC",
      "points": [
        [
          -4235.0,
          1875.0
        ],
        [
          -3061.0,
          1875.0
        ]
      ],
      "width": 1174.0,
      "room": "room_2"
    }
  ],
  "furniture": [
    {
      "id": "12E9",
      "category": "unknown_furniture",
      "points": [
        [
          1158.563366,
          -1447.976385
        ],
        [
          2000.000186,
          -1447.976385
        ],
        [
          2000.000186,
          1446.976263
        ],
        [
          1158.563366,
          1446.976263
        ]
      ],
      "room": "room_1",
      "rotation": -90.00021046,
      "source_block_name": "F-0-0",
      "layer": "roomitems"
    },
    {
      "id": "12EA",
      "category": "unknown_furniture",
      "points": [
        [
          -2000.000911,
          -827.57019
        ],
        [
          -1553.999399,
          -827.57019
        ],
        [
          -1553.999399,
          972.43019
        ],
        [
          -2000.000911,
          972.43019
        ]
      ],
      "room": "room_1",
      "rotation": -270.00005842,
      "source_block_name": "F-0-1",
      "layer": "roomitems"
    },
    {
      "id": "12EE",
      "category": "countertop",
      "points": [
        [
          -5120.007098,
          -1749.992951
        ],
        [
          -4446.672682,
          -1749.992951
        ],
        [
          -4446.672682,
          -550.307049
        ],
        [
          -5120.007098,
          -550.307049
        ]
      ],
      "room": "room_2",
      "rotation": -90.00021046,
      "source_block_name": "F-1-0",
      "layer": "kitchen"
    },
    {
      "id": "12EF",
      "category": "sink",
      "points": [
        [
          -5114.419853,
          -544.529963
        ],
        [
          -4447.67992,
          -544.529963
        ],
        [
          -4447.67992,
          159.769988
        ],
        [
          -5114.419853,
          159.769988
        ]
      ],
      "room": "room_2",
      "source_block_name": "F-1-1",
      "layer": "roomitems"
    },
    {
      "id": "12F0",
      "category": "sink",
      "points": [
        [
          -5111.862293,
          171.609104
        ],
        [
          -4444.137519,
          171.609104
        ],
        [
          -4444.137519,
          911.070856
        ],
        [
          -5111.862293,
          911.070856
        ]
      ],
      "room": "room_2",
      "rotation": -270.00005842,
      "source_block_name": "F-1-2",
      "layer": "roomitems"
    },
    {
      "id": "12F1",
      "category": "countertop",
      "points": [
        [
          -5119.996414,
          917.137026
        ],
        [
          -4439.963366,
          917.137026
        ],
        [
          -4439.963366,
          1750.002974
        ],
        [
          -5119.996414,
          1750.002974
        ]
      ],
      "room": "room_2",
      "rotation": -90.00021046,
      "source_block_name": "F-1-3",
      "layer": "kitchen"
    },
    {
      "id": "12F2",
      "category": "table",
      "points": [
        [
          -3629.077588,
          -279.727041
        ],
        [
          -2515.682192,
          -279.727041
        ],
        [
          -2515.682192,
          1197.887041
        ],
        [
          -3629.077588,
          1197.887041
        ]
      ],
      "room": "room_2",
      "rotation": -90.00021046,
      "source_block_name": "F-1-4",
      "layer": "roomitems"
    },
    {
      "id": "12F5",
      "category": "bed",
      "points": [
        [
          940.692062,
          -4870.001288
        ],
        [
          2000.007938,
          -4870.001288
        ],
        [
          2000.007938,
          -2640.198492
        ],
        [
          940.692062,
          -2640.198492
        ]
      ],
      "room": "room_5",
      "rotation": -179.99984796,
      "source_block_name": "F-2-0",
      "layer": "roomitems"
    },
    {
      "id": "12F8",
      "category": "bathtub",
      "points": [
        [
          -5119.99989,
          -2809.974898
        ],
        [
          -3119.99989,
          -2809.974898
        ],
        [
          -3119.99989,
          -1870.004882
        ],
        [
          -5119.99989,
          -1870.004882
        ]
      ],
      "room": "room_4",
      "source_block_name": "F-3-0",
      "layer": "roomitems"
    },
    {
      "id": "12F9",
      "category": "toilet",
      "points": [
        [
          -5113.903006,
          -4101.183119
        ],
        [
          -4447.102565,
          -4101.183119
        ],
        [
          -4447.102565,
          -3024.121916
        ],
        [
          -5113.903006,
          -3024.121916
        ]
      ],
      "room": "room_4",
      "rotation": -90.00021046,
      "source_block_name": "F-3-1",
      "layer": "plumbing"
    },
    {
      "id": "12FA",
      "category": "sink",
      "points": [
        [
          -5119.995291,
          -4870.000214
        ],
        [
          -4422.865058,
          -4870.000214
        ],
        [
          -4422.865058,
          -4107.099537
        ],
        [
          -5119.995291,
          -4107.099537
        ]
      ],
      "room": "room_4",
      "rotation": -270.00005842,
      "source_block_name": "F-3-2",
      "layer": "roomitems"
    }
  ],
  "rooms": [
    {
      "id": "room_1",
      "name": "Bedroom",
      "area": [
        [
          -1959.098,
          -1682.859
        ],
        [
          -1959.098,
          -1713.598
        ],
        [
          -1928.359,
          -1713.598
        ],
        [
          -1928.359,
          -1744.336
        ],
        [
          -1159.902,
          -1744.336
        ],
        [
          -1159.902,
          -1682.859
        ],
        [
          -1067.687,
          -1682.859
        ],
        [
          -1067.687,
          -1713.598
        ],
        [
          -1036.949,
          -1713.598
        ],
        [
          -1036.949,
          -1744.336
        ],
        [
          -545.137,
          -1744.336
        ],
        [
          -545.137,
          -1713.598
        ],
        [
          -514.398,
          -1713.598
        ],
        [
          -514.398,
          -1682.859
        ],
        [
          -422.184,
          -1682.859
        ],
        [
          -422.184,
          -1744.336
        ],
        [
          346.273,
          -1744.336
        ],
        [
          346.273,
          -1713.598
        ],
        [
          377.012,
          -1713.598
        ],
        [
          377.012,
          -1682.859
        ],
        [
          469.227,
          -1682.859
        ],
        [
          469.227,
          -1713.598
        ],
        [
          499.965,
          -1713.598
        ],
        [
          499.965,
          -1744.336
        ],
        [
          2006.141,
          -1744.336
        ],
        [
          2006.141,
          1759.828
        ],
        [
          899.563,
          1759.828
        ],
        [
          899.563,
          1698.352
        ],
        [
          868.824,
          1698.352
        ],
        [
          868.824,
          1667.613
        ],
        [
          838.086,
          1667.613
        ],
        [
          838.086,
          1636.875
        ],
        [
          684.395,
          1636.875
        ],
        [
          684.395,
          1667.613
        ],
        [
          653.656,
          1667.613
        ],
        [
          653.656,
          1759.828
        ],
        [
          -637.352,
          1759.828
        ],
        [
          -637.352,
          1698.352
        ],
        [
          -668.09,
          1698.352
        ],
        [
          -668.09,
          1667.613
        ],
        [
          -698.828,
          1667.613
        ],
        [
          -698.828,
          1636.875
        ],
        [
          -852.52,
          1636.875
        ],
        [
          -852.52,
          1667.613
        ],
        [
          -883.258,
          1667.613
        ],
        [
          -883.258,
          1759.828
        ],
        [
          -1989.836,
          1759.828
        ],
        [
          -1989.836,
          -1682.859
        ]
      ],
      "area_m2": 13.926026,
      "windows": [
        "12E7"
      ],
      "doors": [
        "12E8",
        "12F4"
      ],
      "walls": [
        "12E4:13",
        "12E4:16",
        "12E4:17",
        "12E4:4",
        "12E4:5",
        "12E4:7",
        "12E5:1",
        "12E5:2",
        "12E5:3"
      ],
      "furniture": [
        "12E9",
        "12EA"
      ]
    },
    {
      "id": "room_2",
      "name": "Kitchen",
      "area": [
        [
          -3096.414,
          -1744.336
        ],
        [
          -3096.414,
          -1775.074
        ],
        [
          -3034.938,
          -1775.074
        ],
        [
          -3034.938,
          -1744.336
        ],
        [
          -2174.266,
          -1744.336
        ],
        [
          -2174.266,
          1759.828
        ],
        [
          -2942.723,
          1759.828
        ],
        [
          -2942.723,
          1667.613
        ],
        [
          -2973.461,
          1667.613
        ],
        [
          -2973.461,
          1636.875
        ],
        [
          -3127.152,
          1636.875
        ],
        [
          -3127.152,
          1667.613
        ],
        [
          -3157.891,
          1667.613
        ],
        [
          -3157.891,
          1698.352
        ],
        [
          -3188.629,
          1698.352
        ],
        [
          -3188.629,
          1759.828
        ],
        [
          -4110.777,
          1759.828
        ],
        [
          -4110.777,
          1698.352
        ],
        [
          -4141.516,
          1698.352
        ],
        [
          -4141.516,
          1667.613
        ],
        [
          -4172.254,
          1667.613
        ],
        [
          -4172.254,
          1636.875
        ],
        [
          -4325.945,
          1636.875
        ],
        [
          -4325.945,
          1698.352
        ],
        [
          -4356.684,
          1698.352
        ],
        [
          -4356.684,
          1759.828
        ],
        [
          -5125.141,
          1759.828
        ],
        [
          -5125.141,
          -1744.336
        ]
      ],
      "area_m2": 10.290273,
      "windows": [
        "12EC"
      ],
      "doors": [
        "12ED"
      ],
      "walls": [
        "12E3:1",
        "12E3:2",
        "12E3:3",
        "12E5:7"
      ],
      "furniture": [
        "12EE",
        "12EF",
        "12F0",
        "12F1",
        "12F2"
      ]
    },
    {
      "id": "room_3",
      "name": "Hallway",
      "area": [
        [
          -2450.91,
          -4848.902
        ],
        [
          -2450.91,
          -4787.426
        ],
        [
          -2420.172,
          -4787.426
        ],
        [
          -2420.172,
          -4756.687
        ],
        [
          -2389.434,
          -4756.687
        ],
        [
          -2389.434,
          -4725.949
        ],
        [
          -2297.219,
          -4725.949
        ],
        [
          -2297.219,
          -4756.687
        ],
        [
          -2235.742,
          -4756.687
        ],
        [
          -2235.742,
          -4818.164
        ],
        [
          -2205.004,
          -4818.164
        ],
        [
          -2205.004,
          -4848.902
        ],
        [
          -1559.5,
          -4848.902
        ],
        [
          -1559.5,
          -4787.426
        ],
        [
          -1528.762,
          -4787.426
        ],
        [
          -1528.762,
          -4756.687
        ],
        [
          -1498.023,
          -4756.687
        ],
        [
          -1498.023,
          -4725.949
        ],
        [
          -1375.07,
          -4725.949
        ],
        [
          -1375.07,
          -4756.687
        ],
        [
          -1344.332,
          -4756.687
        ],
        [
          -1344.332,
          -4787.426
        ],
        [
          -1313.594,
          -4787.426
        ],
        [
          -1313.594,
          -4848.902
        ],
        [
          -883.258,
          -4848.902
        ],
        [
          -883.258,
          -1867.289
        ],
        [
          -1036.949,
          -1867.289
        ],
        [
          -1036.949,
          -1928.766
        ],
        [
          -1159.902,
          -1928.766
        ],
        [
          -1159.902,
          -1867.289
        ],
        [
          -1928.359,
          -1867.289
        ],
        [
          -1928.359,
          -1898.027
        ],
        [
          -1959.098,
          -1898.027
        ],
        [
          -1959.098,
          -1928.766
        ],
        [
          -2174.266,
          -1928.766
        ],
        [
          -2174.266,
          -1867.289
        ],
        [
          -3004.199,
          -1867.289
        ],
        [
          -3004.199,
          -3434.941
        ],
        [
          -2942.723,
          -3434.941
        ],
        [
          -2942.723,
          -3557.895
        ],
        [
          -3004.199,
          -3557.895
        ],
        [
          -3004.199,
          -4326.352
        ],
        [
          -2942.723,
          -4326.352
        ],
        [
          -2942.723,
          -4449.305
        ],
        [
          -3004.199,
          -4449.305
        ],
        [
          -3004.199,
          -4848.902
        ]
      ],
      "area_m2": 6.239734,
      "windows": [],
      "doors": [
        "12E8",
        "12ED",
        "12F7",
        "12FC"
      ],
      "walls": [
        "12E3:10",
        "12E3:13",
        "12E3:4",
        "12E4:1:m2",
        "12E4:4",
        "12E4:5"
      ],
      "furniture": []
    },
    {
      "id": "room_4",
      "name": "Bathroom",
      "area": [
        [
          -3127.152,
          -4879.641
        ],
        [
          -3127.152,
          -4449.305
        ],
        [
          -3157.891,
          -4449.305
        ],
        [
          -3157.891,
          -4418.566
        ],
        [
          -3188.629,
          -4418.566
        ],
        [
          -3188.629,
          -4357.09
        ],
        [
          -3157.891,
          -4357.09
        ],
        [
          -3157.891,
          -4326.352
        ],
        [
          -3127.152,
          -4326.352
        ],
        [
          -3127.152,
          -3557.895
        ],
        [
          -3157.891,
          -3557.895
        ],
        [
          -3157.891,
          -3527.156
        ],
        [
          -3188.629,
          -3527.156
        ],
        [
          -3188.629,
          -3434.941
        ],
        [
          -3127.152,
          -3434.941
        ],
        [
          -3127.152,
          -1867.289
        ],
        [
          -5125.141,
          -1867.289
        ],
        [
          -5125.141,
          -4879.641
        ]
      ],
      "area_m2": 6.006363,
      "windows": [],
      "doors": [
        "12F7"
      ],
      "walls": [
        "12E3:10",
        "12E3:3",
        "12E3:4",
        "12E3:8",
        "12E3:9"
      ],
      "furniture": [
        "12F8",
        "12F9",
        "12FA"
      ]
    },
    {
      "id": "room_5",
      "name": "Bedroom",
      "area": [
        [
          2006.141,
          -4879.641
        ],
        [
          2006.141,
          -1867.289
        ],
        [
          499.965,
          -1867.289
        ],
        [
          499.965,
          -1898.027
        ],
        [
          469.227,
          -1898.027
        ],
        [
          469.227,
          -1928.766
        ],
        [
          377.012,
          -1928.766
        ],
        [
          377.012,
          -1898.027
        ],
        [
          346.273,
          -1898.027
        ],
        [
          346.273,
          -1867.289
        ],
        [
          -391.445,
          -1867.289
        ],
        [
          -391.445,
          -1898.027
        ],
        [
          -422.184,
          -1898.027
        ],
        [
          -422.184,
          -1928.766
        ],
        [
          -514.398,
          -1928.766
        ],
        [
          -514.398,
          -1898.027
        ],
        [
          -545.137,
          -1898.027
        ],
        [
          -545.137,
          -1867.289
        ],
        [
          -668.09,
          -1867.289
        ],
        [
          -668.09,
          -4879.641
        ]
      ],
      "area_m2": 8.040608,
      "windows": [],
      "doors": [
        "12F4"
      ],
      "walls": [
        "12E4:1",
        "12E4:12",
        "12E4:13",
        "12E4:7"
      ],
      "furniture": [
        "12F5"
      ]
    }
  ],
  "warnings": []
}